CHANGELOG.md
README.md
mitol/__init__.py
mitol/transcoding/__init__.py
mitol/transcoding/api.py
mitol/transcoding/apps.py
mitol/transcoding/constants.py
mitol/transcoding/exceptions.py
mitol/transcoding/py.typed
mitol/transcoding/urls.py
mitol/transcoding/utils.py
mitol/transcoding/views.py
mitol/transcoding/settings/__init__.py
mitol/transcoding/settings/job.py
mitol_django_transcoding-2025.5.21.dist-info/METADATA
mitol_django_transcoding-2025.5.21.dist-info/WHEEL
mitol_django_transcoding-2025.5.21.dist-info/RECORD
