Metadata-Version: 2.4
Name: mitol-django-transcoding
Version: 2025.5.21
Summary: MIT Open Learning Django app extension for Transcoding jobs
License-Expression: BSD-3-Clause
Requires-Python: >=3.10
Requires-Dist: boto3<2.0,>=1.37.11
Requires-Dist: django-stubs>=1.13.1
Requires-Dist: django>=3.0
Requires-Dist: mitol-django-common
